{
  "comparisonId": "pablo_picasso:vincent_van_gogh",
  "artist1Id": "6",
  "artist1Name": "Pablo Picasso",
  "artist2Id": "7",
  "artist2Name": "Vincent van Gogh",
  "analysisText": "## Pablo Picasso vs Vincent van Gogh 비교 분석\n\n두 작가는 **담론(discourse)** 지표에서 가장 유사한 패턴을 보입니다. 둘 다 미술 담론에 혁명적 영향을 미쳤으며, 사후에도 끊임없는 학술적 논의의 대상이 됩니다.\n\n### 주요 유사점\n- 후기인상파/표현주의에서 현대미술로의 전환기 핵심 인물\n- 색채의 감정적 표현에 대한 혁신적 접근\n- 자화상을 통한 자아 탐구\n- 생전에는 제한적 상업적 성공, 사후 미술사적 거장으로 재평가\n- 프랑스를 중심으로 활동\n\n### 주요 차이점\n- **수명**: 반 고흐는 37세에 요절, 피카소는 91세까지 장수하며 60년 이상 활동\n- **생산량**: 피카소 5만점+, 반 고흐 약 2,100점\n- **스타일 변화**: 피카소는 청색시대-입체파-초현실주의 등 끊임없이 변화, 반 고흐는 10년간 집약적 발전\n- **인정 시기**: 피카소는 20대부터 인정, 반 고흐는 생전 단 한 작품만 판매\n- **정신건강**: 반 고흐는 심각한 정신질환, 피카소는 상대적으로 안정된 삶\n- **작업 방식**: 반 고흐는 열정적 즉흥, 피카소는 계산된 실험\n\n### 큐레이토리얼 인사이트\n반 고흐와 피카소는 현대미술의 두 기둥입니다. 반 고흐가 감정의 직접적 표현과 색채의 해방을 통해 표현주의의 문을 열었다면, 피카소는 형태의 해체와 재구성을 통해 입체파와 현대미술의 다양한 실험을 가능케 했습니다. 반 고흐의 비극적 생애와 '고통받는 천재' 신화는 그의 작품에 감정적 깊이를 더하고, 피카소의 긴 생애와 다작은 현대미술의 백과사전과 같은 역할을 합니다. 두 작가 모두 프랑스에서 활동했지만, 반 고흐는 파리와 남프랑스에서 4년, 피카소는 평생 파리와 남프랑스를 중심으로 활동했습니다. 피카소는 반 고흐에게 깊은 존경을 표했으며, '아를의 침실'을 재해석한 작품을 남기기도 했습니다.",
  "sharedMetric": "discourse",
  "trajectoryData": [
    {
      "age": 20,
      "a1_total": 30,
      "a1_institution": 15,
      "a1_discourse": 35,
      "a1_academy": 25,
      "a1_network": 40,
      "a1_context": "청색 시대 시작, 파리 정착",
      "a2_total": 2,
      "a2_institution": 0,
      "a2_discourse": 0,
      "a2_academy": 0,
      "a2_network": 5,
      "a2_context": "구필 화상 런던 지점 근무"
    },
    {
      "age": 22,
      "a1_total": 35,
      "a1_institution": 20,
      "a1_discourse": 40,
      "a1_academy": 28,
      "a1_network": 45,
      "a1_context": "청색 시대 절정, La Vie",
      "a2_total": 2,
      "a2_institution": 0,
      "a2_discourse": 0,
      "a2_academy": 0,
      "a2_network": 5,
      "a2_context": "구필 화상 파리 전근"
    },
    {
      "age": 24,
      "a1_total": 42,
      "a1_institution": 28,
      "a1_discourse": 48,
      "a1_academy": 32,
      "a1_network": 52,
      "a1_context": "장미빛 시대 시작",
      "a2_total": 1,
      "a2_institution": 0,
      "a2_discourse": 0,
      "a2_academy": 0,
      "a2_network": 3,
      "a2_context": "암스테르담 신학 공부"
    },
    {
      "age": 26,
      "a1_total": 60,
      "a1_institution": 40,
      "a1_discourse": 85,
      "a1_academy": 45,
      "a1_network": 65,
      "a1_context": "아비뇽의 처녀들",
      "a2_total": 2,
      "a2_institution": 0,
      "a2_discourse": 0,
      "a2_academy": 0,
      "a2_network": 5,
      "a2_context": "보리나주 광부촌 전도사"
    },
    {
      "age": 28,
      "a1_total": 65,
      "a1_institution": 48,
      "a1_discourse": 88,
      "a1_academy": 50,
      "a1_network": 70,
      "a1_context": "분석적 입체파 시작",
      "a2_total": 5,
      "a2_institution": 0,
      "a2_discourse": 0,
      "a2_academy": 5,
      "a2_network": 10,
      "a2_context": "화가 수업 시작"
    },
    {
      "age": 30,
      "a1_total": 70,
      "a1_institution": 55,
      "a1_discourse": 90,
      "a1_academy": 60,
      "a1_network": 75,
      "a1_context": "분석적 입체파 절정",
      "a2_total": 8,
      "a2_institution": 0,
      "a2_discourse": 5,
      "a2_academy": 8,
      "a2_network": 12,
      "a2_context": "드렌테 황야 시기"
    },
    {
      "age": 32,
      "a1_total": 72,
      "a1_institution": 58,
      "a1_discourse": 88,
      "a1_academy": 62,
      "a1_network": 78,
      "a1_context": "종합적 입체파, 콜라주",
      "a2_total": 15,
      "a2_institution": 5,
      "a2_discourse": 12,
      "a2_academy": 15,
      "a2_network": 20,
      "a2_context": "감자 먹는 사람들"
    },
    {
      "age": 34,
      "a1_total": 73,
      "a1_institution": 60,
      "a1_discourse": 85,
      "a1_academy": 64,
      "a1_network": 80,
      "a1_context": "제1차 세계대전 중 파리",
      "a2_total": 30,
      "a2_institution": 12,
      "a2_discourse": 35,
      "a2_academy": 25,
      "a2_network": 45,
      "a2_context": "파리 이주, 인상파 영향"
    },
    {
      "age": 36,
      "a1_total": 75,
      "a1_institution": 65,
      "a1_discourse": 85,
      "a1_academy": 68,
      "a1_network": 82,
      "a1_context": "발레 뤼스 협업",
      "a2_total": 42,
      "a2_institution": 18,
      "a2_discourse": 55,
      "a2_academy": 30,
      "a2_network": 48,
      "a2_context": "별이 빛나는 밤"
    },
    {
      "age": 38,
      "a1_total": 76,
      "a1_institution": 68,
      "a1_discourse": 82,
      "a1_academy": 70,
      "a1_network": 84,
      "a1_context": "신고전주의 회귀",
      "a2_total": 55,
      "a2_institution": 35,
      "a2_discourse": 65,
      "a2_academy": 45,
      "a2_network": 60,
      "a2_context": "사후 첫 회고전 (사후)"
    },
    {
      "age": 40,
      "a1_total": 78,
      "a1_institution": 70,
      "a1_discourse": 83,
      "a1_academy": 72,
      "a1_network": 85,
      "a1_context": "세 명의 음악가",
      "a2_total": 60,
      "a2_institution": 42,
      "a2_discourse": 70,
      "a2_academy": 52,
      "a2_network": 65,
      "a2_context": "명성 확산 (사후)"
    },
    {
      "age": 50,
      "a1_total": 83,
      "a1_institution": 78,
      "a1_discourse": 87,
      "a1_academy": 78,
      "a1_network": 88,
      "a1_context": "미노타우로스 시리즈",
      "a2_total": 70,
      "a2_institution": 55,
      "a2_discourse": 78,
      "a2_academy": 62,
      "a2_network": 72,
      "a2_context": "서간집 출판 (사후)"
    },
    {
      "age": 56,
      "a1_total": 90,
      "a1_institution": 85,
      "a1_discourse": 98,
      "a1_academy": 88,
      "a1_network": 92,
      "a1_context": "게르니카 완성",
      "a2_total": 75,
      "a2_institution": 65,
      "a2_discourse": 82,
      "a2_academy": 70,
      "a2_network": 78,
      "a2_context": "국제적 명성 (사후)"
    },
    {
      "age": 60,
      "a1_total": 88,
      "a1_institution": 84,
      "a1_discourse": 92,
      "a1_academy": 86,
      "a1_network": 90,
      "a1_context": "MoMA 대규모 회고전",
      "a2_total": 80,
      "a2_institution": 70,
      "a2_discourse": 85,
      "a2_academy": 75,
      "a2_network": 80,
      "a2_context": "Armory Show 소개 (사후)"
    },
    {
      "age": 68,
      "a1_total": 92,
      "a1_institution": 90,
      "a1_discourse": 95,
      "a1_academy": 92,
      "a1_network": 92,
      "a1_context": "평화의 비둘기",
      "a2_total": 85,
      "a2_institution": 80,
      "a2_discourse": 88,
      "a2_academy": 82,
      "a2_network": 85,
      "a2_context": "표현주의 선구자 (사후)"
    },
    {
      "age": 74,
      "a1_total": 93,
      "a1_institution": 92,
      "a1_discourse": 94,
      "a1_academy": 93,
      "a1_network": 93,
      "a1_context": "알제의 여인들 시리즈",
      "a2_total": 88,
      "a2_institution": 85,
      "a2_discourse": 90,
      "a2_academy": 86,
      "a2_network": 88,
      "a2_context": "Van Gogh Museum (사후)"
    },
    {
      "age": 80,
      "a1_total": 95,
      "a1_institution": 95,
      "a1_discourse": 96,
      "a1_academy": 95,
      "a1_network": 94,
      "a1_context": "80세 회고전",
      "a2_total": 92,
      "a2_institution": 88,
      "a2_discourse": 93,
      "a2_academy": 90,
      "a2_network": 92,
      "a2_context": "세계적 아이콘 (사후)"
    }
  ],
  "sources": [
    {
      "uri": "https://www.museupicasso.bcn.cat/",
      "title": "Museu Picasso Barcelona"
    },
    {
      "uri": "https://www.musee-picasso.fr/",
      "title": "Musee Picasso Paris"
    },
    {
      "uri": "https://www.vangoghmuseum.nl/",
      "title": "Van Gogh Museum Amsterdam"
    },
    {
      "uri": "https://www.moma.org/",
      "title": "MoMA Archives"
    }
  ],
  "metadata": {
    "version": "1.1.0",
    "lastUpdated": "2025-12-11",
    "primarySources": [
      "Museu Picasso Barcelona",
      "Musee Picasso Paris",
      "Van Gogh Museum Amsterdam",
      "MoMA Archives",
      "Museo Reina Sofia",
      "Tate Modern"
    ],
    "verificationStatus": "verified"
  }
}
